{"avoid_when":"要生产级安全与复杂网络栈","content_hash":"5b48cd0a2c8a23cc72a10ea0d9acc76bd80b8a903346dc9617fe82e14d541fcb","domain":"iot","evidence_urls":["https://github.com/arduino/ArduinoCore-avr"],"id":"arduino-core","language":"C++","license":"","name":"Arduino Core","niche":"maker","repo":"https://github.com/arduino/ArduinoCore-avr","source_updated_at":null,"status":"active","summary":"Arduino AVR 核心（入门嵌入式生态代表）。","tags":["embedded","iot","maker"],"use_when":"教学/创客快速原型","verification_status":"unverified","verified_at":null}
