{"avoid_when":"要超大规模机构级回测平台","content_hash":"784e068e6fd4ca6b9d8c663678e8c79d40763b189c84f0206718e250102b851d","domain":"finance","evidence_urls":["https://github.com/mementum/backtrader"],"id":"backtrader","language":"Python","license":"GPL-3.0","name":"backtrader","niche":"backtest","repo":"https://github.com/mementum/backtrader","source_updated_at":"2024-08-19T17:47:36Z","status":"active","summary":"Python 回测与交易框架。","tags":["backtest","finance","python"],"use_when":"要灵活的 Python 策略回测框架","verification_status":"verified","verified_at":"2026-07-21T13:54:23Z"}
