{"avoid_when":"单机或平台已提供服务发现","content_hash":"748b2e2d0b6fa72c6d08cbc1592d0aabfc9f41e703a2abf7f8e299cadf21219e","domain":"devops","evidence_urls":["https://github.com/hashicorp/consul"],"id":"consul","language":"Go","license":"MPL-2.0 OR BUSL-1.1","name":"Consul","niche":"service discovery","repo":"https://github.com/hashicorp/consul","source_updated_at":"2026-07-21T10:15:49Z","status":"active","summary":"服务发现、配置与网格能力。","tags":["devops","networking"],"use_when":"微服务需要服务发现/健康检查/配置","verification_status":"verified","verified_at":"2026-07-21T14:57:10Z"}
