{"avoid_when":"流量已在边缘 WAF/零信任完整覆盖","content_hash":"fcb68ad5c90a321463f9153b6f4f404cb620da7376d7c25ad69ed0ef75524426","domain":"security","evidence_urls":["https://github.com/fail2ban/fail2ban"],"id":"fail2ban","language":"Python","license":"GPL-2.0","name":"Fail2Ban","niche":"host intrusion prevention","repo":"https://github.com/fail2ban/fail2ban","source_updated_at":"2026-06-23T23:16:17Z","status":"active","summary":"根据日志封禁暴力破解来源。","tags":["hardening","network"],"use_when":"主机要防 SSH/服务爆破","verification_status":"verified","verified_at":"2026-07-21T14:57:10Z"}
