{"avoid_when":"只要单一 XGBoost 栈","content_hash":"4467d0929c41cdc6fc49e47e4084ca3f2e602bc79a13b693a1a2e1bf57aeacef","domain":"data-ml","evidence_urls":["https://github.com/microsoft/LightGBM"],"id":"lightgbm","language":"C++","license":"MIT","name":"LightGBM","niche":"gbdt","repo":"https://github.com/microsoft/LightGBM","source_updated_at":"2026-07-20T03:33:02Z","status":"active","summary":"高效梯度提升框架。","tags":["ml","python"],"use_when":"要更快/更省的 GBDT","verification_status":"verified","verified_at":"2026-07-21T13:52:28Z"}
