{"avoid_when":"要媒体库管理与多用户服务","content_hash":"115148a3da38aa46441228b94c1e95f75039bb9fe4698523060ae8d3d30b9e45","domain":"media","evidence_urls":["https://github.com/mpv-player/mpv"],"id":"mpv","language":"C","license":"GPL-2.0","name":"mpv","niche":"player","repo":"https://github.com/mpv-player/mpv","source_updated_at":"2026-07-14T19:13:03Z","status":"active","summary":"基于 mplayer/mplayer2 的自由媒体播放器。","tags":["media","player","video"],"use_when":"要可脚本化、高可控的本地播放器","verification_status":"verified","verified_at":"2026-07-21T14:57:10Z"}
