{"avoid_when":"只要开箱场景编辑器（Godot）或 WebGL 库","content_hash":"82a3d0da93e1a1b4febfc1cb9159541358bcfc0e1006ea5bee03743e55b19c09","domain":"gamedev","evidence_urls":["https://github.com/OGRECave/ogre"],"id":"ogre","language":"C++","license":"MIT","name":"OGRE","niche":"3d rendering engine","repo":"https://github.com/OGRECave/ogre","source_updated_at":"2026-07-21T20:57:00Z","status":"active","summary":"成熟的面向对象 3D 渲染引擎。","tags":["gamedev"],"use_when":"要可嵌入的 3D 渲染引擎而非完整游戏引擎编辑器","verification_status":"verified","verified_at":"2026-07-21T20:57:00Z"}
