{"avoid_when":"只要 Git 驱动的文档站","content_hash":"3c7cc5c79f73681e401d68ffbc1e014bd068f928dbba1fb92ac13ccea5cc4ea2","domain":"cms-docs","evidence_urls":["https://github.com/strapi/strapi"],"id":"strapi","language":"JavaScript","license":"MIT","name":"Strapi","niche":"headless cms","repo":"https://github.com/strapi/strapi","source_updated_at":"2026-07-21T15:04:08Z","status":"active","summary":"开源无头 CMS，可自托管。","tags":["cms","headless","node"],"use_when":"要自托管无头 CMS 给多前端供内容","verification_status":"verified","verified_at":"2026-07-21T14:57:10Z"}
