{"avoid_when":"深度依赖 Electron 专用生态与 Node 原生模块","content_hash":"cd868bb7a854291fafc645193352ba3149c2701cfadab0449c2419838667693c","domain":"desktop","evidence_urls":["https://github.com/tauri-apps/tauri"],"id":"tauri","language":"Rust","license":"Apache-2.0","name":"Tauri","niche":"webview desktop","repo":"https://github.com/tauri-apps/tauri","source_updated_at":"2026-07-21T08:38:42Z","status":"active","summary":"Rust 后端 + 系统 WebView 的轻量桌面框架。","tags":["cross-platform","desktop","rust"],"use_when":"要更小安装包与更强系统安全边界的桌面应用","verification_status":"verified","verified_at":"2026-07-21T13:52:28Z"}
