{"avoid_when":"只要静态站点生成或无头 CMS API","content_hash":"5f69335c0c86afee834d7c53be54b768ca72ab5ec1755b53579782ebbc6c6b8a","domain":"cms-docs","evidence_urls":["https://github.com/requarks/wiki"],"id":"wikijs","language":"JavaScript","license":"AGPL-3.0","name":"Wiki.js","niche":"wiki","repo":"https://github.com/requarks/wiki","source_updated_at":"2026-07-21T21:04:37Z","status":"active","summary":"基于 Node.js 的现代 Wiki，支持多存储后端与 Markdown。","tags":["docs","nodejs","self-hosted","wiki"],"use_when":"要自托管现代 Wiki 并接 Git/DB 等存储","verification_status":"verified","verified_at":"2026-07-21T21:04:37Z"}
